clustersupport/__init__.py
clustersupport/clustering_results.py
clustersupport/feature_methods.py
clustersupport/optimisation_methods.py
clustersupport-0.0.9.dist-info/LICENSE
clustersupport-0.0.9.dist-info/METADATA
clustersupport-0.0.9.dist-info/WHEEL
clustersupport-0.0.9.dist-info/top_level.txt
clustersupport-0.0.9.dist-info/RECORD
