Metadata-Version: 2.1
Name: clustersupport
Version: 0.0.9
Summary: A small package for enhancing scikit-learn's clustering capabilities
Home-page: https://github.com/mgreenig/ClusterSupport
Author: Matthew Greenig
Author-email: matt.greenig@gmail.com
License: UNKNOWN
Platform: UNKNOWN
Classifier: Programming Language :: Python :: 3
Classifier: License :: OSI Approved :: MIT License
Classifier: Operating System :: OS Independent
Requires-Python: >=3.6
Requires-Dist: scikit-learn (~=0.22.1)
Requires-Dist: clustersupport (~=0.0.1)
Requires-Dist: numpy (~=1.18.1)
Requires-Dist: pandas (~=1.0.3)
Requires-Dist: scipy (~=1.4.1)
Requires-Dist: matplotlib (~=3.1.3)
Requires-Dist: setuptools (~=46.1.3)
